{"name":"Available Tests and Panels","id":"add-order;available-tests-and-panels","testSteps":[{"number":1,"description":"Given User logs in and visits Home page","duration":5143,"startTime":"2023-02-23T13:31:11.410Z[Etc/UTC]","result":"SUCCESS","precondition":false,"level":0},{"number":2,"description":"And User clicks add order and goes to Add order Page","duration":1380,"startTime":"2023-02-23T13:31:16.554Z[Etc/UTC]","result":"SUCCESS","precondition":false,"level":0},{"number":3,"description":"When User Clicks on + Button next to Sample","duration":1140,"startTime":"2023-02-23T13:31:17.934Z[Etc/UTC]","result":"SUCCESS","precondition":false,"level":0},{"number":4,"description":"And User Selects Sample Type from Drop down menu","duration":502,"startTime":"2023-02-23T13:31:19.075Z[Etc/UTC]","result":"SUCCESS","precondition":false,"level":0},{"number":5,"description":"Then Tests entry is marked mandatory","duration":108,"startTime":"2023-02-23T13:31:19.577Z[Etc/UTC]","result":"SUCCESS","precondition":false,"level":0},{"number":6,"description":"And Available Tests exists","duration":79,"startTime":"2023-02-23T13:31:19.685Z[Etc/UTC]","result":"SUCCESS","precondition":false,"level":0},{"number":7,"description":"When User Checks checkbox next to test name","duration":1819,"startTime":"2023-02-23T13:31:19.764Z[Etc/UTC]","result":"SUCCESS","precondition":false,"level":0},{"number":8,"description":"Then Checkbox sticks, test name appears under Tests box","duration":45,"startTime":"2023-02-23T13:31:21.583Z[Etc/UTC]","result":"SUCCESS","precondition":false,"level":0},{"number":9,"description":"When User unChecks checkbox next to test name","duration":1519,"startTime":"2023-02-23T13:31:21.628Z[Etc/UTC]","result":"SUCCESS","precondition":false,"level":0},{"number":10,"description":"Then Name disappears from Tests box","duration":36,"startTime":"2023-02-23T13:31:23.147Z[Etc/UTC]","result":"SUCCESS","precondition":false,"level":0},{"number":11,"description":"When User Checks checkbox next to Panel name","duration":868,"startTime":"2023-02-23T13:31:23.184Z[Etc/UTC]","result":"SUCCESS","precondition":false,"level":0},{"number":12,"description":"Then All applicable panel tests apear in the Testsbox","duration":175,"startTime":"2023-02-23T13:31:24.052Z[Etc/UTC]","result":"SUCCESS","precondition":false,"level":0},{"number":13,"description":"When User unChecks checkbox next to Panel name","duration":801,"startTime":"2023-02-23T13:31:24.228Z[Etc/UTC]","result":"SUCCESS","precondition":false,"level":0},{"number":14,"description":"Then All Test Names disappears from Tests box","duration":258,"startTime":"2023-02-23T13:31:25.030Z[Etc/UTC]","result":"SUCCESS","precondition":false,"level":0},{"number":15,"description":"When User enters Text in Tests Box","duration":98,"startTime":"2023-02-23T13:31:25.288Z[Etc/UTC]","result":"SUCCESS","precondition":false,"level":0},{"number":16,"description":"Then Text cannot be entered in Tests Box","duration":168,"startTime":"2023-02-23T13:31:25.387Z[Etc/UTC]","result":"SUCCESS","precondition":false,"level":0},{"number":17,"description":"When User deletes Text in Tests Box","duration":1886,"startTime":"2023-02-23T13:31:25.556Z[Etc/UTC]","result":"SUCCESS","precondition":false,"level":0},{"number":18,"description":"Then Text cannot be cleared in Tests Box","duration":215,"startTime":"2023-02-23T13:31:27.442Z[Etc/UTC]","result":"SUCCESS","precondition":false,"level":0}],"userStory":{"id":"add-order","storyName":"Add Order","path":"openelis/addOrder.feature","type":"feature"},"featureTag":{"name":"Openelis/Add Order","type":"feature","displayName":"Openelis/Add Order"},"title":"Available Tests and Panels","description":"","backgroundTitle":"","backgroundDescription":"","tags":[{"name":"order","type":"tag","displayName":"order"}],"startTime":"2023-02-23T13:31:10.967Z[Etc/UTC]","duration":16776,"projectKey":"","isManualTestingUpToDate":false,"manual":false,"testSource":"Cucumber","result":"SUCCESS"}